roverpro/__init__.py
roverpro/booty_protocol.py
roverpro/find_device.py
roverpro/pitstop.py
roverpro/rover.py
roverpro/rover_data.py
roverpro/rover_protocol.py
roverpro/serial_trio.py
roverpro/tests/__init__.py
roverpro/tests/burnin/__init__.py
roverpro/tests/burnin/conftest.py
roverpro/tests/burnin/test_burnin.py
roverpro/tests/conftest.py
roverpro/tests/resources/PowerBoard-1.5.0.hex
roverpro/tests/resources/powerboard-1.0.6.hex
roverpro/tests/test_bootloader.py
roverpro/tests/test_find_device.py
roverpro/tests/test_rover.py
roverpro/tests/test_rover_protocol.py
roverpro/util.py
roverpro-1.0.1.dist-info/entry_points.txt
roverpro-1.0.1.dist-info/LICENSE.txt
roverpro-1.0.1.dist-info/WHEEL
roverpro-1.0.1.dist-info/METADATA
roverpro-1.0.1.dist-info/RECORD
