Metadata-Version: 2.1
Name: roverpro
Version: 1.0.1
Summary: A Python driver for driving the Rover Robotics Rover Pro robot
Home-page: https://github.com/RoverRobotics/roverpro-python
License: BSD-3-Clause
Author: Dan Rose
Author-email: dan@digilabs.io
Maintainer: Dan Rose
Maintainer-email: dan@digilabs.io
Requires-Python: >=3.6,<4.0
Classifier: Framework :: Trio
Classifier: License :: OSI Approved :: BSD License
Classifier: Operating System :: OS Independent
Classifier: Programming Language :: Python :: 3
Classifier: Programming Language :: Python :: 3.6
Classifier: Programming Language :: Python :: 3.7
Classifier: Programming Language :: Python :: 3.8
Classifier: Programming Language :: Python :: 3.9
Requires-Dist: async_generator (>=1.10,<2.0)
Requires-Dist: booty (>=0.3.0,<0.4.0)
Requires-Dist: pyserial (>=3.4,<4.0)
Requires-Dist: pytest (>=5.4.3,<6.0.0)
Requires-Dist: pytest-trio (>=0.6.0,<0.7.0)
Requires-Dist: trio (>=0.16.0,<0.17.0)
Project-URL: Repository, https://github.com/RoverRobotics/roverpro-python
